cooc_ar_stemmer/__init__.py
cooc_ar_stemmer/ar_stem.py
cooc_ar_stemmer/dic.pkl
cooc_ar_stemmer/mx.pkl
cooc_ar_stemmer/vectorizer.pkl
cooc_ar_stemmer-0.1.1.dist-info/LICENSE.txt
cooc_ar_stemmer-0.1.1.dist-info/METADATA
cooc_ar_stemmer-0.1.1.dist-info/WHEEL
cooc_ar_stemmer-0.1.1.dist-info/top_level.txt
cooc_ar_stemmer-0.1.1.dist-info/RECORD
