Metadata-Version: 2.2
Name: cooc_ar_stemmer
Version: 0.1.1
Summary: A stemmer for the Arabic language
Home-page: https://github.com/iskander-akhmetov/cooc_ar_stemmer
Author: Iskander Akhmetov
Author-email: iskander.akhmetov@gmail.com
License: Proprietary
Classifier: Programming Language :: Python :: 3
Classifier: License :: Other/Proprietary License
Classifier: Operating System :: OS Independent
Requires-Python: >=3.11.7
License-File: LICENSE.txt
Dynamic: author
Dynamic: author-email
Dynamic: classifier
Dynamic: description
Dynamic: description-content-type
Dynamic: home-page
Dynamic: license
Dynamic: requires-python
Dynamic: summary
